arango_orm/__init__.py
arango_orm/collections.py
arango_orm/config.py
arango_orm/connection_pool.py
arango_orm/database.py
arango_orm/event.py
arango_orm/exceptions.py
arango_orm/graph.py
arango_orm/query.py
arango_orm/references.py
arango_orm-1.1.0.dist-info/LICENSE.txt
arango_orm-1.1.0.dist-info/METADATA
arango_orm-1.1.0.dist-info/WHEEL
arango_orm-1.1.0.dist-info/RECORD
