Metadata-Version: 2.1
Name: arango-orm
Version: 1.1.0
Summary: A SQLAlchemy like ORM implementation for arangodb
Home-page: https://arango-orm.compulife.com.pk
License: GNU General Public License v2 (GPLv2)
Author: Kashif Iftikhar
Author-email: kashif@compulife.com.pk
Requires-Python: >=3.11,<4.0
Classifier: License :: Other/Proprietary License
Classifier: Programming Language :: Python :: 3
Classifier: Programming Language :: Python :: 3.11
Requires-Dist: pydantic (>=2.3.0,<3.0.0)
Requires-Dist: python-arango (>=7.6.2,<8.0.0)
Project-URL: Repository, https://github.com/kashifpk/arango-orm
